nonebot_plugin_arcaea_sticker-0.4.5.dist-info/METADATA
nonebot_plugin_arcaea_sticker-0.4.5.dist-info/WHEEL
nonebot_plugin_arcaea_sticker-0.4.5.dist-info/entry_points.txt
nonebot_plugin_arcaea_sticker-0.4.5.dist-info/licenses/LICENSE
nonebot_plugin_arcaea_sticker/__init__.py
nonebot_plugin_arcaea_sticker/config.py
nonebot_plugin_arcaea_sticker/fonts/ShangShouFangTangTi.woff2
nonebot_plugin_arcaea_sticker/fonts/YurukaFangTang.ttf
nonebot_plugin_arcaea_sticker/fonts/YurukaStd.woff2
nonebot_plugin_arcaea_sticker/help.py
nonebot_plugin_arcaea_sticker/img/aichan.png
nonebot_plugin_arcaea_sticker/img/arcaea_stickers.png
nonebot_plugin_arcaea_sticker/img/ayu.png
nonebot_plugin_arcaea_sticker/img/eto.png
nonebot_plugin_arcaea_sticker/img/hikari.png
nonebot_plugin_arcaea_sticker/img/hikari2.png
nonebot_plugin_arcaea_sticker/img/ilith.png
nonebot_plugin_arcaea_sticker/img/insight.png
nonebot_plugin_arcaea_sticker/img/kanae.png
nonebot_plugin_arcaea_sticker/img/kou.png
nonebot_plugin_arcaea_sticker/img/lagrange.png
nonebot_plugin_arcaea_sticker/img/lethe.png
nonebot_plugin_arcaea_sticker/img/luna.png
nonebot_plugin_arcaea_sticker/img/maya.png
nonebot_plugin_arcaea_sticker/img/nami.png
nonebot_plugin_arcaea_sticker/img/nonoka.png
nonebot_plugin_arcaea_sticker/img/saya.png
nonebot_plugin_arcaea_sticker/img/shirabe.png
nonebot_plugin_arcaea_sticker/img/shirahime.png
nonebot_plugin_arcaea_sticker/img/tairitsu.png
nonebot_plugin_arcaea_sticker/img/tairitsu2.png
nonebot_plugin_arcaea_sticker/img/tairitsu3.png
nonebot_plugin_arcaea_sticker/img/vita.png
nonebot_plugin_arcaea_sticker/models.py
nonebot_plugin_arcaea_sticker/render.py
nonebot_plugin_arcaea_sticker/resource.py
nonebot_plugin_arcaea_sticker/templates/help.html.jinja
nonebot_plugin_arcaea_sticker/templates/help.svg.jinja
nonebot_plugin_arcaea_sticker/templates/sticker.svg.jinja
nonebot_plugin_arcaea_sticker/templates/sticker_grid.html.jinja
nonebot_plugin_arcaea_sticker/text.py
nonebot_plugin_arcaea_sticker-0.4.5.dist-info/RECORD
