Metadata-Version: 2.1
Name: nonebot-plugin-arcaea-sticker
Version: 0.4.5
Summary: Arcaea sticker generator plugin for NoneBot2 with cross-platform support (Python 3.12+ compatible)
Keywords: nonebot2,plugin,arcaea,sticker
Author-Email: JQ-28 <480352716@qq.com>
License: MIT
Project-URL: homepage, https://github.com/JQ-28/nonebot-plugin-arcaea-sticker
Project-URL: repository, https://github.com/JQ-28/nonebot-plugin-arcaea-sticker
Project-URL: documentation, https://github.com/JQ-28/nonebot-plugin-arcaea-sticker#readme
Requires-Python: <4.0,>=3.8
Requires-Dist: nonebot2>=2.0.0
Requires-Dist: nonebot-plugin-alconna>=0.50.0
Requires-Dist: nonebot-plugin-htmlrender>=0.2.0
Requires-Dist: nonebot-plugin-localstore>=0.7.0
Requires-Dist: Pillow>=9.0.0
Requires-Dist: jinja2>=3.0.0
Requires-Dist: anyio>=3.0.0
Requires-Dist: yarl>=1.0.0
Requires-Dist: pydantic>=2.0.0
